LICENSE
MANIFEST.in
README.md
setup.py
version
pytp/__init__.py
pytp.egg-info/PKG-INFO
pytp.egg-info/SOURCES.txt
pytp.egg-info/dependency_links.txt
pytp.egg-info/requires.txt
pytp.egg-info/top_level.txt
pytp/utils/__init__.py
pytp/utils/augment.py
pytp/utils/evaluate.py
pytp/utils/get_velocity.py
pytp/utils/normalize.py